[
  {
    "id":10,
    "gk-easting":3572983,
    "gk-northing":5358494,
    "wgs84-east":9.98500873,
    "wgs84-north":48.36103098
  },
  {
    "id":100,
    "gk-easting":3573290,
    "gk-northing":5362865,
    "wgs84-east":9.98991339,
    "wgs84-north":48.40030235
  },
  {
    "id":101,
    "gk-easting":3573087,
    "gk-northing":5368102,
    "wgs84-east":9.98808443,
    "wgs84-north":48.44742014
  },
  {
    "id":102,
    "gk-easting":3566855,
    "gk-northing":5357806,
    "wgs84-east":9.90220459,
    "wgs84-north":48.35552223
  },
  {
    "id":103,
    "gk-easting":3571745,
    "gk-northing":5357513,
    "wgs84-east":9.96813549,
    "wgs84-north":48.35235093
  },
  {
    "id":104,
    "gk-easting":3573874,
    "gk-northing":5363626,
    "wgs84-east":9.99793400,
    "wgs84-north":48.40707759
  },
  {
    "id":12,
    "gk-easting":3573975,
    "gk-northing":5364406,
    "wgs84-east":9.99943561,
    "wgs84-north":48.41407997
  },
  {
    "id":13,
    "gk-easting":3571505,
    "gk-northing":5366475,
    "wgs84-east":9.96642251,
    "wgs84-north":48.43297076
  },
  {
    "id":14,
    "gk-easting":3571884,
    "gk-northing":5366620,
    "wgs84-east":9.97156897,
    "wgs84-north":48.43423157
  },
  {
    "id":15,
    "gk-easting":3571001,
    "gk-northing":5364055,
    "wgs84-east":9.95920213,
    "wgs84-north":48.41126549
  },
  {
    "id":16,
    "gk-easting":3572365,
    "gk-northing":5362381,
    "wgs84-east":9.97733812,
    "wgs84-north":48.39605671
  },
  {
    "id":17,
    "gk-easting":3569871,
    "gk-northing":5367072,
    "wgs84-east":9.94444093,
    "wgs84-north":48.43852274
  },
  {
    "id":18,
    "gk-easting":3574363,
    "gk-northing":5363372,
    "wgs84-east":10.00449367,
    "wgs84-north":48.40473600
  },
  {
    "id":19,
    "gk-easting":3573256,
    "gk-northing":5367926,
    "wgs84-east":9.99033806,
    "wgs84-north":48.44581782
  },
  {
    "id":20,
    "gk-easting":3572227,
    "gk-northing":5357224,
    "wgs84-east":9.97458912,
    "wgs84-north":48.34969711
  },
  {
    "id":21,
    "gk-easting":3572128,
    "gk-northing":5361705,
    "wgs84-east":9.97402172,
    "wgs84-north":48.39000479
  },
  {
    "id":23,
    "gk-easting":3573040,
    "gk-northing":5362464,
    "wgs84-east":9.98646749,
    "wgs84-north":48.39672530
  },
  {
    "id":24,
    "gk-easting":3566701,
    "gk-northing":5357811,
    "wgs84-east":9.90012743,
    "wgs84-north":48.35558347
  },
  {
    "id":25,
    "gk-easting":3569515,
    "gk-northing":5363089,
    "wgs84-east":9.93896962,
    "wgs84-north":48.40274408
  },
  {
    "id":26,
    "gk-easting":3575828,
    "gk-northing":5366409,
	"wgs84-east":10.02482843,	
    "wgs84-north":48.43187179
  },
  {
    "id":27,
    "gk-easting":3579660,
    "gk-northing":5361561,
    "wgs84-east":9.95104,
    "wgs84-north":48.40603
  },
  {
    "id":28,
    "gk-easting":3565093,
    "gk-northing":5358670,
    "wgs84-east":9.87856305,
    "wgs84-north":48.36347618
  },
  {
    "id":29,
    "gk-easting":3572734,
    "gk-northing":5358305,
    "wgs84-east":9.98161597,
    "wgs84-north":48.35936008
  },
  {
    "id":30,
    "gk-easting":3574161,
    "gk-northing":5365216,
    "wgs84-east":10.00209131,
    "wgs84-north":48.42134210
  },
  {
    "id":31,
    "gk-easting":3572205,
    "gk-northing":5362411,
    "wgs84-east":9.97518270,
    "wgs84-north":48.39634482
  },
  {
    "id":32,
    "gk-easting":3573943,
    "gk-northing":5363634,
    "wgs84-east":9.99886736,
    "wgs84-north":48.40714145
  },
  {
    "id":33,
    "gk-easting":3570516,
    "gk-northing":5362406,
    "wgs84-east":9.95237397,
    "wgs84-north":48.39649092
  },
  {
    "id":34,
    "gk-easting":3575434,
    "gk-northing":5366152,
    "wgs84-east":10.01945810,
    "wgs84-north":48.42960802
  },
  {
    "id":35,
    "gk-easting":3570565,
    "gk-northing":5362496,
    "wgs84-east":9.95305077,
    "wgs84-north":48.39729479
  },
  {
    "id":36,
    "gk-easting":3571723,
    "gk-northing":5355291,
    "wgs84-east":9.96746042,
    "wgs84-north":48.33237147
  },
  {
    "id":37,
    "gk-easting":3572526,
    "gk-northing":5357494,
    "wgs84-east":9.97866954,
    "wgs84-north":48.35209090
  },
  {
    "id":38,
    "gk-easting":3571356,
    "gk-northing":5361404,
    "wgs84-east":9.96354701,
    "wgs84-north":48.38738576
  },
  {
    "id":39,
    "gk-easting":3573848,
    "gk-northing":5363834,
    "wgs84-east":9.99761942,
    "wgs84-north":48.40895110
  },
  {
    "id":40,
    "gk-easting":3572161,
    "gk-northing":5357485,
    "wgs84-east":9.97374341,
    "wgs84-north":48.35205176
  },
  {
    "id":41,
    "gk-easting":3570973,
    "gk-northing":5364089,
    "wgs84-east":9.95882967,
    "wgs84-north":48.41157439
  },
  {
    "id":42,
    "gk-easting":3571501,
    "gk-northing":5361836,
    "wgs84-east":9.96557821,
    "wgs84-north":48.39125420
  },
  {
    "id":44,
    "gk-easting":3574131,
    "gk-northing":5363132,
    "wgs84-east":10.00131795,
    "wgs84-north":48.40260509
  },
  {
    "id":45,
    "gk-easting":3571529,
    "gk-northing":5363599,
    "wgs84-east":9.96625651,
    "wgs84-north":48.40710515
  },
  {
    "id":46,
    "gk-easting":3570482,
    "gk-northing":5364191,
    "wgs84-east":9.95221445,
    "wgs84-north":48.41254673
  },
  {
    "id":47,
    "gk-easting":3573175,
    "gk-northing":5362854,
    "wgs84-east":9.98835844,
    "wgs84-north":48.40021679
  },
  {
    "id":48,
    "gk-easting":3573518,
    "gk-northing":5363360,
    "wgs84-east":9.99307912,
    "wgs84-north":48.40472716
  },
  {
    "id":49,
    "gk-easting":3573150,
    "gk-northing":5363969,
    "wgs84-east":9.98821506,
    "wgs84-north":48.41024646
  },
  {
    "id":51,
    "gk-easting":3572693,
    "gk-northing":5358250,
    "wgs84-east":9.98105323,
    "wgs84-north":48.35887020
  },
  {
    "id":52,
    "gk-easting":3569388,
    "gk-northing":5355161,
    "wgs84-east":9.93594701,
    "wgs84-north":48.33146297
  },
  {
    "id":53,
    "gk-easting":3574579,
    "gk-northing":5363820,
    "wgs84-east":10.00749050,
    "wgs84-north":48.40873917
  },
  {
    "id":54,
    "gk-easting":3566375,
    "gk-northing":5360871,
    "wgs84-east":9.89621140,
    "wgs84-north":48.38313615
  },
  {
    "id":55,
    "gk-easting":3569808,
    "gk-northing":5359759,
    "wgs84-east":9.94237365,
    "wgs84-north":48.37276578
  },
  {
    "id":56,
    "gk-easting":3569998,
    "gk-northing":5364440,
    "wgs84-east":9.94571805,
    "wgs84-north":48.41483984
  },
  {
    "id":57,
    "gk-easting":3569879,
    "gk-northing":5364427,
    "wgs84-east":9.94410835,
    "wgs84-north":48.41473614
  },
  {
    "id":58,
    "gk-easting":3572570,
    "gk-northing":5357478,
    "wgs84-east":9.97926043,
    "wgs84-north":48.35194196
  },
  {
    "id":59,
    "gk-easting":3572498,
    "gk-northing":5357527,
    "wgs84-east":9.97829744,
    "wgs84-north":48.35239087
  },
  {
    "id":6,
    "gk-easting":3573184,
    "gk-northing":5367986,
    "wgs84-east":9.98937533,
    "wgs84-north":48.44636574
  },
  {
    "id":60,
    "gk-easting":3571460,
    "gk-northing":5364541,
    "wgs84-east":9.96548492,
    "wgs84-north":48.41558407
  },
  {
    "id":61,
    "gk-easting":3570053,
    "gk-northing":5361875,
    "wgs84-east":9.94603314,
    "wgs84-north":48.39176735
  },
  {
    "id":62,
    "gk-easting":3571304,
    "gk-northing":5361502,
    "wgs84-east":9.96286156,
    "wgs84-north":48.38827293
  },
  {
    "id":63,
    "gk-easting":3570275,
    "gk-northing":5364512,
    "wgs84-east":9.94947202,
    "wgs84-north":48.41545650
  },
  {
    "id":64,
    "gk-easting":3572100,
    "gk-northing":5357906,
    "wgs84-east":9.97299248,
    "wgs84-north":48.35584467
  },
  {
    "id":65,
    "gk-easting":3569523,
    "gk-northing":5355477,
    "wgs84-east":9.93781984,
    "wgs84-north":48.33428989
  },
  {
    "id":66,
    "gk-easting":3570774,
    "gk-northing":5364001,
    "wgs84-east":9.95612677,
    "wgs84-north":48.41080540
  },
  {
    "id":67,
    "gk-easting":3573667,
    "gk-northing":5363306,
    "wgs84-east":9.99508202,
    "wgs84-north":48.40422418
  },
  {
    "id":68,
    "gk-easting":3573034,
    "gk-northing":5362154,
    "wgs84-east":9.98633257,
    "wgs84-north":48.39393828
  },
  {
    "id":69,
    "gk-easting":3572407,
    "gk-northing":5361375,
    "wgs84-east":9.97773193,
    "wgs84-north":48.38700526
  },
  {
    "id":7,
    "gk-easting":3575659,
    "gk-northing":5366388,
    "wgs84-east":10.02254096,
    "wgs84-north":48.43170327
  },
  {
    "id":70,
    "gk-easting":3576291,
    "gk-northing":5366872,
    "wgs84-east":10.03116916,
    "wgs84-north":48.43597941
  },
  {
    "id":71,
    "gk-easting":3572592,
    "gk-northing":5358230,
    "wgs84-east":9.97968690,
    "wgs84-north":48.35870196
  },
  {
    "id":72,
    "gk-easting":3574888,
    "gk-northing":5363766,
    "wgs84-east":10.01165448,
    "wgs84-north":48.40821695
  },
  {
    "id":8,
    "gk-easting":3572231,
    "gk-northing":5363681,
    "wgs84-east":9.97575223,
    "wgs84-north":48.40776253
  },
  {
    "id":80,
    "gk-easting":3572362,
    "gk-northing":5362458,
    "wgs84-east":9.97731088,
    "wgs84-north":48.39674949
  },
  {
    "id":81,
    "gk-easting":3575054,
    "gk-northing":5363787,
    "wgs84-east":10.01390035,
    "wgs84-north":48.40838605
  },
  {
    "id":82,
    "gk-easting":3573066,
    "gk-northing":5361956,
    "wgs84-east":9.98673024,
    "wgs84-north":48.39215403
  },
  {
    "id":83,
    "gk-easting":3571990,
    "gk-northing":5361445,
    "wgs84-east":9.97211390,
    "wgs84-north":48.38768245
  },
  {
    "id":84,
    "gk-easting":3569930,
    "gk-northing":5362618,
    "wgs84-east":9.94449599,
    "wgs84-north":48.39846262
  },
  {
    "id":85,
    "gk-easting":3575195,
    "gk-northing":5363878,
    "wgs84-east":10.01582110,
    "wgs84-north":48.40918758
  },
  {
    "id":86,
    "gk-easting":3571936,
    "gk-northing":5361129,
    "wgs84-east":9.97133074,
    "wgs84-north":48.38484692
  },
  {
    "id":87,
    "gk-easting":3571935,
    "gk-northing":5365197,
    "wgs84-east":9.97201408,
    "wgs84-north":48.42142923
  },
  {
    "id":88,
    "gk-easting":3569526,
    "gk-northing":5364524,
    "wgs84-east":9.93935584,
    "wgs84-north":48.41564746
  },
  {
    "id":89,
    "gk-easting":3572407,
    "gk-northing":5361375,
    "wgs84-east":9.97773193,
    "wgs84-north":48.38700526
  },
  {
    "id":9,
    "gk-easting":3570361,
    "gk-northing":5361808,
    "wgs84-east":9.95018072,
    "wgs84-north":48.39113056
  },
  {
    "id":90,
    "gk-easting":3571073,
    "gk-northing":5362428,
    "wgs84-east":9.95989932,
    "wgs84-north":48.39662625
  },
  {
    "id":91,
    "gk-easting":3571615,
    "gk-northing":5362099,
    "wgs84-east":9.96716231,
    "wgs84-north":48.39360635
  },
  {
    "id":92,
    "gk-easting":3571268,
    "gk-northing":5364521,
    "wgs84-east":9.96288782,
    "wgs84-north":48.41542595
  },
  {
    "id":94,
    "gk-easting":3568389,
    "gk-northing":5362854,
    "wgs84-east":9.92372404,
    "wgs84-north":48.40075387
  },
  {
    "id":97,
    "gk-easting":3570760,
    "gk-northing":5363824,
    "wgs84-east":9.95590783,
    "wgs84-north":48.40921527
  },
  {
    "id":98,
    "gk-easting":3571592,
    "gk-northing":5366661,
    "wgs84-east":9.96762994,
    "wgs84-north":48.43463351
  }
]
